{
  "suvicharList" : [

    {
      "suvichar" : "પહેલો હોય કે છેલ્લો અક્ષર,\nઆવે છે એકસમાન\nહું છું એક એવી ભાષા,\nજવાબ આપો તો તમે સાચા.",
      "arth" : "મલયાલમ"
    },
    {
      "suvichar" : "આમ તો નીચી નજરે ચાલે,\nરીસાય ત્યારે પગ પછાડે,\nલોકોનો એ ભાર વેંઢારે,\nતોય કોઇ સારો ન માને.",
      "arth" : "ગધેડો"
    },
    {
      "suvichar" : "તણખલા રૂના સંગાથે,\nઝૂલું ડાળે ડાળ,\nજ્યારે પંખી ઊડી જાતા,\nબચ્ચાની રાખું સંભાળ.",
      "arth" : "માળો"
    },
    {
      "suvichar" : "બોખું બોખું મોં ફરે, કરે મઝાની વાતો,\nઆખા ઘરમાં ખુલ્લો મુકે, વાર્તાનો ખજાનો.",
      "arth" : "દાદા-દાદી"
    },
    {
      "suvichar" : "મા ગોરી રૂપકડી,\nને બચ્ચા કાળાં મેશ,\nમા મરે, બચ્ચા જો ભળે,\nદૂધ-ચામાં સુગંધ પ્રસરે.",
      "arth" : "એલચી"
    },
    {
      "suvichar" : "લીલુ ફળને ધોળું બી,\nમારે માથે કાંટા,\nચોમાસામાં મને સેવો તો,\nટળે દવાખાનાના આંટા.",
      "arth" : "કારેલુ"
    },
    {
      "suvichar" : "લાગે ઢમઢોલ શરીર,\nપણ નથી મારો કંઇ ભાર,\nદેહ છે મારો રંગબેરંગી,\nબાળકોનો છું હું સંગી.",
      "arth" : "ફુગ્ગો"
    },
    {
      "suvichar" : "નદી-સરોવરમાં રહેતી,\nપાણીની રાણી કહેવાતી,\nરંગબેરંગી જોવા મળતી,\nકહો ક્યા નામે ઓળખાતી ?",
      "arth" : "માછલી"
    },
    {
      "suvichar" : "આખો દિવસ ઊંધ્યા કરું,\nરાત પડે ને રડ્યા કરું,\nજેટલું રડું એટલું ગુમાવું ?\nતો બોલો મિત્રો કોણ હું ?",
      "arth" : "મિણબત્તી"
    },
    {
      "suvichar" : "સાત વેંતનું સાપોલિયું,\nમુખે લોઢાનાં દાંત,\nનારી સાથે રમત રમુ,\nજોઇને હસે કાંત.",
      "arth" : "સાંબેલુ."
    },
    {
      "suvichar" : "ઉડું છું પણ પંખી નહીં\nસૂંઢ છે પણ હાથી નહી\nછ પગ પણ માખી નહી\nગીત ગાઉં છું પણ ભમરો નહીં.",
      "arth" : "મચ્છર"
    },
    {
      "suvichar" : "ગોળ ગોળ ફરતી જાય\nફરતી ફરતી ગાતી જાય\nદાણો દાણો ખાતી જાય\nતોય એનુ પેટ ન ભરાય.",
      "arth" : "ઘંટી"
    },
    {
      "suvichar" : "ચાર ભાઇ આડા ચાર ભાઈ ઉભા\nએક એકના અંગમાં બબ્બે જણ બેઠા.",
      "arth" : "ખાટલો"
    },
    {
      "suvichar" : "જીભ વગર ટકટક કરે, ચાલે પણ નહીં પગ\nકાંટા પણ વાગે નહીં જાણે આખું જગ",
      "arth" : "ઘડિયાળ"
    },
    {
      "suvichar" : "ચાર ખૂણાનું ચોકઠું આભે ઉડ્યુ જાય,\nરાજા પૂછે રાણીને આ ક્યુ જનાવર જાય.",
      "arth" : "પતંગ"
    },
    {
      "suvichar" : "ફાળ ભરે પણ મૃગ નહી,\nનહી સસલો નહી શ્વાન.\nમો ઉચુ પણ મોર નહી,",
      "arth" : "દેડકો"
    },
    {
      "suvichar" : "પગ વિના ડુંગરે ચડે, મુખ વિના ખડ ખાય,\nરાણી કહે રળિયામણું, ક્યુ જનાવર જાય ?",
      "arth" : "ધૂમાડો"
    },
    {
      "suvichar" : "પઢતો પણ પંડિત નહી, પૂર્યો પણ નહી ચોર,\nચતુર હોય તો ચેતજો, મધૂરો પણ નહી મોર.",
      "arth" : "ભમરો"
    },
    {
      "suvichar" : "તેર પગાળો તેતરો નેળિયે નાઠો જાય,\nરાજા પૂછે રાણીને આ ક્યુ જનાવર જાય.",
      "arth" : "બળદગાડુ"
    },
    {
      "suvichar" : "મારી બકરી આલો પાલો ખાય,\nપાણી પીવે તો ટપ દઈને મરી જાય.",
      "arth" : " દેવતા"
    },
    {
      "suvichar" : "પશુ નહી પણ ચાર પગ, એક વાંહો બે શિશ,\nબાળક તેના પેટમાં, એ શી ચીજ કહીશ ?",
      "arth" : "ઘોડીયું"
    },
    {
      "suvichar" : "એક અચરજ એવુ જોયુ, નદી છતા નહી નીર\nપહાડ છતા પથ્થર નહી, ગામ છતા નહી વીર.",
      "arth" : "નકશો"
    },
    {
      "suvichar" : "લીલી લીલી સળીઓ ને ગાંઠે ગાંઠે ચોર,\nચોરનું તો તેલ થાયને છોડાં ખાય ઢોર.",
      "arth" : "મગફળી"
    },
    {
      "suvichar" : "ગોળ છુ પણ દડો નથી, પૂંછડી છે પણ રડતો નથી,\nપૂંછડી પકડીને રમે છે બાળકો, તો પણ હુ રડતો નથી.",
      "arth" : "ફુગ્ગો"
    },
    {
      "suvichar" : "એક જળકુકડી એવી જે ડબક ડુબકી મારે\nપચાસ માઇલ પાણીમાં ચાલી, તોપના ગોળા ખાળે.",
      "arth" : "સબમરીન"
    },
    {
      "suvichar" : "નહી વાંસલો, નહી વીંઝણો, નહી કારીગર સુતાર,\nઅદ્ધર મહેલ ચણાવિયો, રાજા કરે વિચાર.",
      "arth" : "વાળ"
    },
    {
      "suvichar" : "વનવગડામાં ડોસો કેડ બાંધી ઉભો.",
      "arth" : "પૂળો"
    },
    {
      "suvichar" : "ચુકડી છોકરીને ટચુકડા કાન.\nગળે બાંધો સિંદરુ (દોરી) તો ઝટ કામ થાય",
      "arth" : "સાવરણી"
    }

  ]
}